reactpy/__init__.py
reactpy/__main__.py
reactpy/_option.py
reactpy/_warnings.py
reactpy/config.py
reactpy/html.py
reactpy/logging.py
reactpy/py.typed
reactpy/sample.py
reactpy/svg.py
reactpy/types.py
reactpy/utils.py
reactpy/widgets.py
reactpy/_client/index.html
reactpy/_client/assets/index.53b29c63.js
reactpy/_client/assets/reactpy-logo.ico
reactpy/_console/__init__.py
reactpy/_console/ast_utils.py
reactpy/_console/rewrite_camel_case_props.py
reactpy/_console/rewrite_keys.py
reactpy/backend/__init__.py
reactpy/backend/_common.py
reactpy/backend/default.py
reactpy/backend/fastapi.py
reactpy/backend/flask.py
reactpy/backend/hooks.py
reactpy/backend/sanic.py
reactpy/backend/starlette.py
reactpy/backend/tornado.py
reactpy/backend/types.py
reactpy/backend/utils.py
reactpy/core/__init__.py
reactpy/core/_f_back.py
reactpy/core/_thread_local.py
reactpy/core/component.py
reactpy/core/events.py
reactpy/core/hooks.py
reactpy/core/layout.py
reactpy/core/serve.py
reactpy/core/types.py
reactpy/core/vdom.py
reactpy/testing/__init__.py
reactpy/testing/backend.py
reactpy/testing/common.py
reactpy/testing/display.py
reactpy/testing/logs.py
reactpy/web/__init__.py
reactpy/web/module.py
reactpy/web/utils.py
reactpy/web/templates/react.js
reactpy-1.0.0.dist-info/LICENSE
reactpy-1.0.0.dist-info/METADATA
reactpy-1.0.0.dist-info/WHEEL
reactpy-1.0.0.dist-info/entry_points.txt
reactpy-1.0.0.dist-info/top_level.txt
reactpy-1.0.0.dist-info/RECORD
