Metadata-Version: 2.1
Name: reactpy
Version: 1.0.0
Summary: It's React, but in Python
Home-page: https://github.com/reactive-python/reactpy
Author: Ryan Morshead
Author-email: ryan.morshead@gmail.com
License: MIT
Keywords: interactive,widgets,DOM,React
Platform: Linux
Platform: Mac OS X
Platform: Windows
Classifier: Environment :: Web Environment
Classifier: Framework :: AsyncIO
Classifier: Framework :: Flask
Classifier: Intended Audience :: Developers
Classifier: Intended Audience :: Science/Research
Classifier: Programming Language :: Python :: 3.7
Classifier: Programming Language :: Python :: 3.8
Classifier: Programming Language :: Python :: 3.9
Classifier: Topic :: Software Development :: User Interfaces
Classifier: Topic :: Software Development :: Widget Sets
Classifier: Typing :: Typed
Requires-Python: >=3.7
Provides-Extra: all
Provides-Extra: starlette
Provides-Extra: sanic
Provides-Extra: fastapi
Provides-Extra: flask
Provides-Extra: tornado
Provides-Extra: testing
License-File: LICENSE
